{"id":"10614","banner":{"ico_pickup":"\u5c0f\u7de8\u7cbe\u9078","title":"\u3010APP\u3011\u5e38\u5e38\u5fd8\u6771\u5fd8\u897f\uff1f\u5c0f\u5e6b\u624b\u6642\u6642\u63d0\u9192 >>"},"cover":{"title":"\u3010\u5be6\u7528\u3011\u518d\u4e5f\u4e0d\u6015\u5fd8\u8a18\u4e8b\u60c5\uff01\u597d\u7528App\u770b\u9019\u88e1","tag":[{"url":"\/tag\/104","name":"\u624b\u6a5f"},{"url":"\/tag\/121","name":"app"},{"url":"\/tag\/128","name":"Android"}],"profile":{"url":"\/my\/2041343","name":"Jeffrey.","photo":"http:\/\/cdn-obs.line-apps.com\/line\/r\/lineq\/p\/11f15e4a-6fa0-4f10-b2d7-41d8db1cea5b229e9481t0612a322\/200x200.round","date":"2016.02.02 09:32"},"view":"14,027 \u6b21\u700f\u89bd","metoo_count":"156","comment_count":"10","source":"https:\/\/pixabay.com\/zh\/\u529e\u516c\u5ba4-\u6ce8\u91ca-\u8bb0\u4e8b\u672c-\u4f01\u4e1a\u5bb6-\u5973\u5546\u4eba-\u884c\u653f-\u4e1a\u52a1-\u4e13\u4e1a-\u6210\u529f-620817\/"},"page":[{"order":"1","text":"\u4f60\u662f\u5426\u5e38\u5e38\u5fd8\u8a18\u300c\u6e96\u6642\u300d\u6253\u96fb\u8a71\u7d66\u5225\u4eba\u3001\u300c\u6e96\u6642\u300d\u6536\u770b\u96fb\u8996\u7bc0\u76ee\u3001\u300c\u6e96\u6642\u300d\u53bb\u7e73\u8cbb......\u7b49\u5462\uff1f\n\n\u6c92\u95dc\u4fc2\uff01\u4e0b\u8f09\u9019\u500bApp\uff0c\u89e3\u6c7a\u4f60\u7684\u7169\u60f1\uff01\n\n\n\u300c\u63d0\u9192\u5e03\u7a40\u300d\nhttps:\/\/play.google.com\/store\/apps\/details?id=danAndJacy.reminder","url":"\/note\/10614\/p\/28808","image":"","image_src":"","content":{"image":"","image_src":"","text":"\u4f60\u662f\u5426\u5e38\u5e38\u5fd8\u8a18\u300c\u6e96\u6642\u300d\u6253\u96fb\u8a71\u7d66\u5225\u4eba\u3001\u300c\u6e96\u6642\u300d\u6536\u770b\u96fb\u8996\u7bc0\u76ee\u3001\u300c\u6e96\u6642\u300d\u53bb\u7e73\u8cbb......\u7b49\u5462\uff1f\n\n\u6c92\u95dc\u4fc2\uff01\u4e0b\u8f09\u9019\u500bApp\uff0c\u89e3\u6c7a\u4f60\u7684\u7169\u60f1\uff01\n\n\n\u300c\u63d0\u9192\u5e03\u7a40\u300d\n<a class=\"url\" href=\"https:\/\/play.google.com\/store\/apps\/details?id=danAndJacy.reminder\" target=\"_blank\">https:\/\/play.google.com\/store\/apps\/details?id=danAndJacy.reminder<\/a>\r\n\t\t\t\t\t\t\t\t"}},{"order":"2","text":"\u63d0\u9192\u8a2d\u5b9a\u9801\u9762","url":"\/note\/10614\/p\/28815","image":"http:\/\/cdn-obs.line-apps.com\/line\/r\/lineq\/c\/1eea90e8-02bd-469c-b3e7-ce3a23e81f75b41e19t03ec273c\/500x500.rf","image_src":"Jeffrey.","content":{"image":"http:\/\/cdn-obs.line-apps.com\/line\/r\/lineq\/c\/1eea90e8-02bd-469c-b3e7-ce3a23e81f75b41e19t03ec273c\/1000x1000.rm","image_src":"\u4f86\u6e90 :Jeffrey.","text":"\u63d0\u9192\u8a2d\u5b9a\u9801\u9762\r\n\t\t\t\t\t\t\t\t"}},{"order":"3","text":"\u63d0\u9192\u8a2d\u5b9a\u7c21\u55ae\u4ecb\u7d39","url":"\/note\/10614\/p\/28816","image":"http:\/\/cdn-obs.line-apps.com\/line\/r\/lineq\/c\/dbb5ba29-6c1e-4c6a-87a7-392e21be7708161e0bt03ec27ad\/500x500.rf","image_src":"Jeffrey.","content":{"image":"http:\/\/cdn-obs.line-apps.com\/line\/r\/lineq\/c\/dbb5ba29-6c1e-4c6a-87a7-392e21be7708161e0bt03ec27ad\/1000x1000.rm","image_src":"\u4f86\u6e90 :Jeffrey.","text":"\u63d0\u9192\u8a2d\u5b9a\u7c21\u55ae\u4ecb\u7d39\r\n\t\t\t\t\t\t\t\t"}},{"order":"4","text":"\u8a2d\u5b9a\u597d\u7684\u6703\u5728\u300c\u4efb\u52d9\u6e05\u55ae\u300d\u5167","url":"\/note\/10614\/p\/28817","image":"http:\/\/cdn-obs.line-apps.com\/line\/r\/lineq\/c\/30443ebd-9df2-4904-9d63-6ac3db67f907791a24t03ec27d6\/500x500.rf","image_src":"Jeffrey.","content":{"image":"http:\/\/cdn-obs.line-apps.com\/line\/r\/lineq\/c\/30443ebd-9df2-4904-9d63-6ac3db67f907791a24t03ec27d6\/1000x1000.rm","image_src":"\u4f86\u6e90 :Jeffrey.","text":"\u8a2d\u5b9a\u597d\u7684\u6703\u5728\u300c\u4efb\u52d9\u6e05\u55ae\u300d\u5167\r\n\t\t\t\t\t\t\t\t"}},{"order":"5","text":"\u6642\u9593\u5230\u4e86\uff0c\u5c31\u6703\u6709\u63d0\u9192\uff01","url":"\/note\/10614\/p\/28818","image":"http:\/\/cdn-obs.line-apps.com\/line\/r\/lineq\/c\/c5e57896-f4d8-44c8-af75-80cfa0ccf984651e11t03ec2804\/500x500.rf","image_src":"Jeffrey.","content":{"image":"http:\/\/cdn-obs.line-apps.com\/line\/r\/lineq\/c\/c5e57896-f4d8-44c8-af75-80cfa0ccf984651e11t03ec2804\/1000x1000.rm","image_src":"\u4f86\u6e90 :Jeffrey.","text":"\u6642\u9593\u5230\u4e86\uff0c\u5c31\u6703\u6709\u63d0\u9192\uff01\r\n\t\t\t\t\t\t\t\t"}},{"order":"6","text":"\u901a\u5e38\u9ede\u64ca\u901a\u77e5\u5f8c\uff0c\u88e1\u9762\u90fd\u53ef\u4ee5\u76f4\u63a5\u4f5c\u696d\uff01\n\u50cf\u662f\u76f4\u63a5\u6253\u7d66\u4ed6\u4e4b\u985e\u7684\uff01","url":"\/note\/10614\/p\/28819","image":"http:\/\/cdn-obs.line-apps.com\/line\/r\/lineq\/c\/cc1734c6-a0c3-4204-b9af-47c6c0c96385791aa8t03ec281c\/500x500.rf","image_src":"Jeffrey.","content":{"image":"http:\/\/cdn-obs.line-apps.com\/line\/r\/lineq\/c\/cc1734c6-a0c3-4204-b9af-47c6c0c96385791aa8t03ec281c\/1000x1000.rm","image_src":"\u4f86\u6e90 :Jeffrey.","text":"\u901a\u5e38\u9ede\u64ca\u901a\u77e5\u5f8c\uff0c\u88e1\u9762\u90fd\u53ef\u4ee5\u76f4\u63a5\u4f5c\u696d\uff01\n\u50cf\u662f\u76f4\u63a5\u6253\u7d66\u4ed6\u4e4b\u985e\u7684\uff01\r\n\t\t\t\t\t\t\t\t"}},{"order":"7","text":"\u300c\u6b77\u53f2\u7d00\u9304\u300d\u662f\u653e\u4e00\u4e9b\u5df2\u904e\u671f(\u505a\u904e)\u7684\u4e8b\u60c5","url":"\/note\/10614\/p\/28820","image":"http:\/\/cdn-obs.line-apps.com\/line\/r\/lineq\/c\/0367af60-25e1-4da0-9853-9402700630a2071a1et03ec28a7\/500x500.rf","image_src":"Jeffrey.","content":{"image":"http:\/\/cdn-obs.line-apps.com\/line\/r\/lineq\/c\/0367af60-25e1-4da0-9853-9402700630a2071a1et03ec28a7\/1000x1000.rm","image_src":"\u4f86\u6e90 :Jeffrey.","text":"\u300c\u6b77\u53f2\u7d00\u9304\u300d\u662f\u653e\u4e00\u4e9b\u5df2\u904e\u671f(\u505a\u904e)\u7684\u4e8b\u60c5\r\n\t\t\t\t\t\t\t\t"}},{"order":"8","text":"App\u8a2d\u5b9a\u6559\u5b78","url":"\/note\/10614\/p\/28821","image":"http:\/\/cdn-obs.line-apps.com\/line\/r\/lineq\/c\/517bd0ad-a98a-4147-ad9b-7c4beb93f9fff21a25t03ec285c\/500x500.rf","image_src":"Jeffrey.","content":{"image":"http:\/\/cdn-obs.line-apps.com\/line\/r\/lineq\/c\/517bd0ad-a98a-4147-ad9b-7c4beb93f9fff21a25t03ec285c\/1000x1000.rm","image_src":"\u4f86\u6e90 :Jeffrey.","text":"App\u8a2d\u5b9a\u6559\u5b78\r\n\t\t\t\t\t\t\t\t"}},{"order":"9","text":"\u9019\u88e1\u90fd\u6703\u6709\u4e00\u4e9b\u8a2d\u7f6e\u53ef\u8a2d\u5b9a","url":"\/note\/10614\/p\/28822","image":"http:\/\/cdn-obs.line-apps.com\/line\/r\/lineq\/c\/f92ad265-f115-4b9a-b6ec-e19e81ea067f601aa7t03ec2895\/500x500.rf","image_src":"Jeffrey.","content":{"image":"http:\/\/cdn-obs.line-apps.com\/line\/r\/lineq\/c\/f92ad265-f115-4b9a-b6ec-e19e81ea067f601aa7t03ec2895\/1000x1000.rm","image_src":"\u4f86\u6e90 :Jeffrey.","text":"\u9019\u88e1\u90fd\u6703\u6709\u4e00\u4e9b\u8a2d\u7f6e\u53ef\u8a2d\u5b9a\r\n\t\t\t\t\t\t\t\t"}},{"order":"10","text":"\u9084\u6709\u5f88\u591a\u63d0\u9192\u53ef\u4ee5\u8a2d\u5b9a\u5594\uff01\n\u50cf\u662f\u300c\u91cd\u8981\u65e5\u671f\u300d","url":"\/note\/10614\/p\/28823","image":"http:\/\/cdn-obs.line-apps.com\/line\/r\/lineq\/c\/fc07f91b-b396-4b37-835f-9a64629c8100f01aa2t03ec28d4\/500x500.rf","image_src":"Jeffrey.","content":{"image":"http:\/\/cdn-obs.line-apps.com\/line\/r\/lineq\/c\/fc07f91b-b396-4b37-835f-9a64629c8100f01aa2t03ec28d4\/1000x1000.rm","image_src":"\u4f86\u6e90 :Jeffrey.","text":"\u9084\u6709\u5f88\u591a\u63d0\u9192\u53ef\u4ee5\u8a2d\u5b9a\u5594\uff01\n\u50cf\u662f\u300c\u91cd\u8981\u65e5\u671f\u300d\r\n\t\t\t\t\t\t\t\t"}},{"order":"11","text":"\u7bc0\u76ee\u8868\u63d0\u9192\n\n\u9084\u6709\u5167\u5efa\u7bc0\u76ee\u8868\uff0c\u5f88\u65b9\u4fbfXDD","url":"\/note\/10614\/p\/28824","image":"http:\/\/cdn-obs.line-apps.com\/line\/r\/lineq\/c\/0f361044-9cb8-4543-9b40-da784ae8ab839d1a52t03ec28f7\/500x500.rf","image_src":"Jeffrey.","content":{"image":"http:\/\/cdn-obs.line-apps.com\/line\/r\/lineq\/c\/0f361044-9cb8-4543-9b40-da784ae8ab839d1a52t03ec28f7\/1000x1000.rm","image_src":"\u4f86\u6e90 :Jeffrey.","text":"\u7bc0\u76ee\u8868\u63d0\u9192\n\n\u9084\u6709\u5167\u5efa\u7bc0\u76ee\u8868\uff0c\u5f88\u65b9\u4fbfXDD\r\n\t\t\t\t\t\t\t\t"}},{"order":"12","text":"\u6e05\u55ae\u63d0\u9192\n\n\u6211\u89ba\u5f97\u9019\u500b\u529f\u80fd\u6700\u597d\u7528XD","url":"\/note\/10614\/p\/28825","image":"http:\/\/cdn-obs.line-apps.com\/line\/r\/lineq\/c\/3e3fbf26-29f5-46d5-94ce-a189e981272ea31a52t03ec2910\/500x500.rf","image_src":"Jeffrey.","content":{"image":"http:\/\/cdn-obs.line-apps.com\/line\/r\/lineq\/c\/3e3fbf26-29f5-46d5-94ce-a189e981272ea31a52t03ec2910\/1000x1000.rm","image_src":"\u4f86\u6e90 :Jeffrey.","text":"\u6e05\u55ae\u63d0\u9192\n\n\u6211\u89ba\u5f97\u9019\u500b\u529f\u80fd\u6700\u597d\u7528XD\r\n\t\t\t\t\t\t\t\t"}},{"order":"13","text":"\u50b3\u8a0a\u606f\u63d0\u9192","url":"\/note\/10614\/p\/28826","image":"http:\/\/cdn-obs.line-apps.com\/line\/r\/lineq\/c\/bccc5cb7-6fbe-41db-8bf0-9423b76c5fb7e81a5ft03ec2942\/500x500.rf","image_src":"Jeffrey.","content":{"image":"http:\/\/cdn-obs.line-apps.com\/line\/r\/lineq\/c\/bccc5cb7-6fbe-41db-8bf0-9423b76c5fb7e81a5ft03ec2942\/1000x1000.rm","image_src":"\u4f86\u6e90 :Jeffrey.","text":"\u50b3\u8a0a\u606f\u63d0\u9192\r\n\t\t\t\t\t\t\t\t"}},{"order":"14","text":"\u7e73\u8cbb\u63d0\u9192\n\n\u5e38\u5e38\u5fd8\u8a18\u7e73\u8cbb\u7684\u66f4\u8981\u7528\u7528\u770b\uff01","url":"\/note\/10614\/p\/28827","image":"http:\/\/cdn-obs.line-apps.com\/line\/r\/lineq\/c\/e232793e-35eb-4655-bd8b-7af0aff35f5e4f1a58t03ec2954\/500x500.rf","image_src":"Jeffrey.","content":{"image":"http:\/\/cdn-obs.line-apps.com\/line\/r\/lineq\/c\/e232793e-35eb-4655-bd8b-7af0aff35f5e4f1a58t03ec2954\/1000x1000.rm","image_src":"\u4f86\u6e90 :Jeffrey.","text":"\u7e73\u8cbb\u63d0\u9192\n\n\u5e38\u5e38\u5fd8\u8a18\u7e73\u8cbb\u7684\u66f4\u8981\u7528\u7528\u770b\uff01\r\n\t\t\t\t\t\t\t\t"}},{"order":"15","text":"\u524d\u5f80\u67d0\u5730 \u7684\u63d0\u9192","url":"\/note\/10614\/p\/28828","image":"http:\/\/cdn-obs.line-apps.com\/line\/r\/lineq\/c\/da6e929c-92c8-42f1-8f36-e5fe481ccd6fde1a31t03ec2971\/500x500.rf","image_src":"Jeffrey.","content":{"image":"http:\/\/cdn-obs.line-apps.com\/line\/r\/lineq\/c\/da6e929c-92c8-42f1-8f36-e5fe481ccd6fde1a31t03ec2971\/1000x1000.rm","image_src":"\u4f86\u6e90 :Jeffrey.","text":"\u524d\u5f80\u67d0\u5730 \u7684\u63d0\u9192\r\n\t\t\t\t\t\t\t\t"}},{"order":"16","text":"\u5403\u85e5\u63d0\u9192","url":"\/note\/10614\/p\/28829","image":"http:\/\/cdn-obs.line-apps.com\/line\/r\/lineq\/c\/aeb7adf6-da6b-44b2-b94d-0bc0d49859d6e51a10t03ec29a7\/500x500.rf","image_src":"Jeffrey.","content":{"image":"http:\/\/cdn-obs.line-apps.com\/line\/r\/lineq\/c\/aeb7adf6-da6b-44b2-b94d-0bc0d49859d6e51a10t03ec29a7\/1000x1000.rm","image_src":"\u4f86\u6e90 :Jeffrey.","text":"\u5403\u85e5\u63d0\u9192\r\n\t\t\t\t\t\t\t\t"}}],"comment":[]}