{"title":"\u6709\u4ec0\u9ebc\u5e6b\u52a9\u8b80\u66f8\u7684App\u55ce\uff1f","author":{"photo":"\/pc\/common\/img\/header_photo_anonymous_50x50.png","name":"\u533f\u540d","time":"2016.08.14 00:14"},"question":{"completed":"Completed","point":"0","content":"\r\n\t              <p class=\"content_text\">\u6709\u4ec0\u9ebc\u5e6b\u52a9\u8b80\u66f8\u7684App\u55ce\uff1f<\/p>\r\n\t              <div class=\"question_report\">\r\n\t                \t\t<a href=\"#\" class=\"report_anchor _reportQuestion\">\u6aa2\u8209<\/a>\r\n\t              <\/div>\r\n\t              <h2 class=\"question_relations\">\r\n\t              \t<i class=\"ico_category\"><\/i>\r\n\t              \t<a href=\"\/tag\/121\" class=\"item\">app<\/a>\u3001\r\n\t              \t<a href=\"\/tag\/576\" class=\"item\">\u8b80\u66f8\u65b9\u6cd5<\/a>\u3001\r\n\t              \t<a href=\"\/tag\/169\" class=\"item\">\u5b78\u7fd2<\/a>\r\n\t              <\/h2>\r\n\t            ","relations":[{"url":"\/tag\/121","category":"app"},{"url":"\/tag\/576","category":"\u8b80\u66f8\u65b9\u6cd5"},{"url":"\/tag\/169","category":"\u5b78\u7fd2"}],"as_metoo":"150"},"answer":{"band":[{"aid":"32128381","status":"\u4e2d\u9078","status_class":"reply_band_wrap as_exactly","author":{"photo":"http:\/\/cdn-obs.line-apps.com\/line\/r\/lineq\/p\/2453e399-6aee-40c1-940e-6a2ef062c627271a0ft04eca062\/48x48.rf","link":"\/my\/1951119","name":"Shania\u2764"},"time":"2016.08.16 02:50","like":"4","contnet":"\n<a class=\"url\" href=\"http:\/\/lineq.tw\/note\/17665\" target=\"_blank\">http:\/\/lineq.tw\/note\/17665<\/a>\n\u53ef\u4ee5\u53c3\u8003\u6211\u7684\u7b46\u8a18QQ","good_list":[]},{"aid":"32085984","status":"Good","status_class":"reply_band_wrap as_good","author":{"photo":"","link":"","name":""},"time":"2016.08.15 08:40","like":"43","contnet":"\u7d55\u5c0d\u4e0d\u8981\u5347\u5b78\u738b\uff0c\u4f60\u8003\u5b8c\u4e4b\u5f8c\u4ed6\u6703\u4e00\u76f4\u6253\u96fb\u8a71\u7169\u4f60","good_list":[]}],"list_count":"21","list":[{"aid":"32041850","status":"","status_class":"","author":{"photo":"","link":"","name":""},"time":"2016.08.14 03:55","like":"18","contnet":"Line Q\n\u6211\u8981\u7576\u5b78\u9738","good_list":[]},{"aid":"32046539","status":"","status_class":"","author":{"photo":"","link":"","name":""},"time":"2016.08.14 11:17","like":"9","contnet":"\u7a2e\u6a39","good_list":[]},{"aid":"32063127","status":"","status_class":"","author":{"photo":"","link":"","name":""},"time":"2016.08.14 18:40","like":"4","contnet":"\u9019\u500b","good_list":[]},{"aid":"32063976","status":"","status_class":"","author":{"photo":"","link":"","name":""},"time":"2016.08.14 19:02","like":"7","contnet":"Forest \u5927\u63a8 \u8003\u6703\u8003\u7684\u6642\u5019\u6211\u90fd\u7528\u9019\u500b","good_list":[]},{"aid":"32085984","status":"","status_class":"","author":{"photo":"","link":"","name":""},"time":"2016.08.15 08:40","like":"43","contnet":"\u7d55\u5c0d\u4e0d\u8981\u5347\u5b78\u738b\uff0c\u4f60\u8003\u5b8c\u4e4b\u5f8c\u4ed6\u6703\u4e00\u76f4\u6253\u96fb\u8a71\u7169\u4f60","good_list":[]},{"aid":"","status":"","status_class":"","author":{"photo":"","link":"","name":""},"time":"2016.08.15 11:15","like":"","contnet":"\u597d\u54e6\uff0c\u6211\u518d\u53bb\u770b\u770b\u8b1d\u8b1d\u5927\u5bb6\u7684\u63a8\u85a6","good_list":[]},{"aid":"32128381","status":"","status_class":"","author":{"photo":"http:\/\/cdn-obs.line-apps.com\/line\/r\/lineq\/p\/2453e399-6aee-40c1-940e-6a2ef062c627271a0ft04eca062\/48x48.rf","link":"\/my\/1951119","name":"Shania\u2764"},"time":"2016.08.16 02:50","like":"4","contnet":"\n<a class=\"url\" href=\"http:\/\/lineq.tw\/note\/17665\" target=\"_blank\">http:\/\/lineq.tw\/note\/17665<\/a>\n\u53ef\u4ee5\u53c3\u8003\u6211\u7684\u7b46\u8a18QQ","good_list":[]},{"aid":"32148364","status":"","status_class":"","author":{"photo":"","link":"","name":""},"time":"2016.08.16 17:34","like":"4","contnet":"@\u533f\u540d5 \u771f\u7684\u771f\u7684\uff01\u6211\u90fd\u653e\u97f3\u6a02\u7d66\u4ed6\u5011\u807dXD","good_list":[]},{"aid":"32149561","status":"","status_class":"","author":{"photo":"","link":"","name":""},"time":"2016.08.16 17:57","like":"2","contnet":"@\u533f\u540d6 \u6211\u4e5f\u6709\u54c8\u54c8\u54c8","good_list":[]},{"aid":"32156211","status":"","status_class":"","author":{"photo":"","link":"","name":""},"time":"2016.08.16 20:10","like":"5","contnet":"\u6211\u8981\u7576\u5b78\u9738 \u8d85\u63a8","good_list":[]},{"aid":"32156453","status":"","status_class":"","author":{"photo":"http:\/\/cdn-obs.line-apps.com\/line\/r\/lineq\/p\/8a952bf7-a362-4757-9c4a-c76a14e20d408e1a90t05351c88\/48x48.rf","link":"\/my\/2131970","name":"\u4ee5\u5176\u4e0d\u722d\uff0c\u6545\u5929\u4e0b\u83ab\u80fd\u8207\u4e4b\u722d"},"time":"2016.08.16 20:15","like":"11","contnet":"\u628a\u624b\u6a5f\u95dc\u6389\uff0c\u5c08\u5fc3\u5538\u66f8\u9589\u95dc\u5230\u8003\u8a66\uff0c\u6700\u5be6\u5728\u3002","good_list":[]},{"aid":"32157031","status":"","status_class":"","author":{"photo":"http:\/\/cdn-obs.line-apps.com\/line\/r\/lineq\/p\/e25a33d5-8c8e-4ad5-8d16-4bdb0ba9985022cf3623t061654a1\/48x48.rf","link":"\/my\/436841","name":"\u5f64\u5594"},"time":"2016.08.16 20:26","like":"2","contnet":"@\u533f\u540d3 \u8acb\u554f\u4f60\u7684\u90a3\u500b\u5728\u54ea\u88e1\u554a play\u5546\u5e97\u597d\u50cf\u6c92\u6709","good_list":[]},{"aid":"32162234","status":"","status_class":"","author":{"photo":"","link":"\/my\/1056731","name":"\u60f3\u4e0d\u5230\u540d\u5b57\u6b38"},"time":"2016.08.16 21:45","like":"1","contnet":"forest\u5927\u63a8\uff01\uff01\uff01\uff01\uff01\uff01","good_list":[]},{"aid":"32162790","status":"","status_class":"","author":{"photo":"","link":"\/my\/2054594","name":"\u4e00\u534a\u6d77\u6c34\u4e00\u534a\u706b\u7130"},"time":"2016.08.16 21:54","like":"3","contnet":"\u53ef\u4ee5\u5148\u7528Google\u65e5\u66c6\u505a\u8b80\u66f8\u8a08\u756b\uff0c\u7528Google Note\u6216Evernote\u4f5c\u7b46\u8a18\uff0c\u5230Google Play\u8f38\u5165\u5b57\u5178\u53ef\u4ee5\u627e\u4e2d\u6587\u6216\u82f1\u6f22\u5b57\u5178\u3002","good_list":[]},{"aid":"32162972","status":"","status_class":"","author":{"photo":"","link":"","name":""},"time":"2016.08.16 21:57","like":"3","contnet":"@\u5f64\u5594 \u9019\u500b","good_list":[]},{"aid":"32167010","status":"","status_class":"","author":{"photo":"http:\/\/cdn-obs.line-apps.com\/line\/r\/lineq\/p\/863ac8c8-3144-4e1c-bae3-468abfc49d5b841a90t03ca5b91\/48x48.rf","link":"\/my\/1995480","name":"winnie_pigpig"},"time":"2016.08.16 23:04","like":"0","contnet":"\u6211\u4e5f\u63a8forest","good_list":[]},{"aid":"32171687","status":"","status_class":"","author":{"photo":"","link":"","name":""},"time":"2016.08.17 00:42","like":"0","contnet":"\u82f1\u6f22\u5b57\u5178","good_list":[]},{"aid":"32197547","status":"","status_class":"","author":{"photo":"http:\/\/cdn-obs.line-apps.com\/line\/r\/lineq\/p\/f52e2180-57e1-46e1-b66f-eaed60926c5fb01aadt051a8e72\/48x48.rf","link":"\/my\/2046141","name":"\u4e9e\u77b3"},"time":"2016.08.17 18:45","like":"0","contnet":"forest\u771f\u7684\u5f88\u4e0d\u932f\uff0c\u6709\u4e0d\u4e00\u6a23\u7684\u52d5\u529b\u4e0d\u78b0\u624b\u6a5f\uff0c\u63a8\u4e00\u500b","good_list":[]},{"aid":"32209755","status":"","status_class":"","author":{"photo":"http:\/\/cdn-obs.line-apps.com\/line\/r\/lineq\/p\/6ccbae5a-e960-4d16-855e-23eabcbcc8a222594383t05f45f21\/48x48.rf","link":"\/my\/2096802","name":"ZYC\u2747"},"time":"2016.08.17 22:20","like":"0","contnet":"Forest\n\u6211\u8981\u7576\u5b78\u9738","good_list":[]},{"aid":"32225609","status":"","status_class":"","author":{"photo":"http:\/\/cdn-obs.line-apps.com\/line\/r\/lineq\/p\/7e18725a-2801-433a-a378-188ad924652f241e0et05a939eb\/48x48.rf","link":"\/my\/2061792","name":"\u25b3\u4e09\u89d2\u25b3"},"time":"2016.08.18 11:44","like":"0","contnet":"\u6709\u4e86\u5b83\uff0c\u9084\u6703\u518d\u7576\u500b\u4f4e\u982d\u65cf\u55ce\uff1f - LINE Q <a class=\"url\" href=\"http:\/\/lineq.tw\/note\/17665\" target=\"_blank\">http:\/\/lineq.tw\/note\/17665<\/a>\n","good_list":[]},{"aid":"32228914","status":"","status_class":"","author":{"photo":"","link":"\/my\/2012471","name":"\u963f\u7136\u7136"},"time":"2016.08.18 13:21","like":"0","contnet":"Study bank","good_list":[]},{"aid":"32234371","status":"","status_class":"","author":{"photo":"","link":"","name":""},"time":"2016.08.18 15:46","like":"0","contnet":"@\u533f\u540d7 Give me fight. XD","good_list":[]}]}}